[
  {
    "id": "3RSU0_HiohUyiO1jASIbazxFDD68cz",
    "ownerId": 50838,
    "name": "Arunoda Susiripala",
    "avatar": "https://avatars1.githubusercontent.com/u/50838?v=4",
    "content": "This is my first comment.\nHow was it.",
    "createdAt": 1593755950851
  },
  {
    "id": "J1CJtPPW_2K66QJH9RdI5KyY4OCTod",
    "ownerId": 50838,
    "name": "Arunoda Susiripala",
    "avatar": "https://avatars1.githubusercontent.com/u/50838?v=4",
    "content": "Wow. Optimistic UI is awesome.",
    "createdAt": 1593755965527
  },
  {
    "id": "CR6bSkwKpTIjGBPObpesFhV1zQKbKR",
    "ownerId": 50838,
    "name": "Arunoda Susiripala",
    "avatar": "https://avatars1.githubusercontent.com/u/50838?v=4",
    "content": "This is a comment made from the production version.",
    "createdAt": 1593756386232
  }
]